LICENSE
MANIFEST.in
README.md
setup.py
src/peakrdl_uvm/__about__.py
src/peakrdl_uvm/__init__.py
src/peakrdl_uvm/__peakrdl__.py
src/peakrdl_uvm/exporter.py
src/peakrdl_uvm/pre_export_listener.py
src/peakrdl_uvm.egg-info/PKG-INFO
src/peakrdl_uvm.egg-info/SOURCES.txt
src/peakrdl_uvm.egg-info/dependency_links.txt
src/peakrdl_uvm.egg-info/entry_points.txt
src/peakrdl_uvm.egg-info/requires.txt
src/peakrdl_uvm.egg-info/top_level.txt
src/peakrdl_uvm/templates/main.sv
src/peakrdl_uvm/templates/top_include.svh
src/peakrdl_uvm/templates/top_pkg.sv
src/peakrdl_uvm/templates/utils.sv
src/peakrdl_uvm/templates/uvm_reg.sv
src/peakrdl_uvm/templates/uvm_reg_block-mem.sv
src/peakrdl_uvm/templates/uvm_reg_block.sv
src/peakrdl_uvm/templates/uvm_vreg.sv