Metadata-Version: 2.1
Name: peakrdl-uvm
Version: 2.3.0
Summary: Generate UVM register model from compiled SystemRDL input
Home-page: https://github.com/SystemRDL/PeakRDL-uvm
Author: Alex Mykyta, Jude Zhang
License: UNKNOWN
Project-URL: Source, https://github.com/SystemRDL/PeakRDL-uvm
Project-URL: Tracker, https://github.com/SystemRDL/PeakRDL-uvm/issues
Platform: UNKNOWN
Classifier: Development Status :: 5 - Production/Stable
Classifier: Programming Language :: Python
Classifier: Programming Language :: Python :: 3
Classifier: Programming Language :: Python :: 3.5
Classifier: Programming Language :: Python :: 3.6
Classifier: Programming Language :: Python :: 3.7
Classifier: Programming Language :: Python :: 3.8
Classifier: Programming Language :: Python :: 3.9
Classifier: Programming Language :: Python :: 3.10
Classifier: Programming Language :: Python :: 3.11
Classifier: Programming Language :: Python :: 3 :: Only
Classifier: Intended Audience :: Developers
Classifier: License :: OSI Approved :: GNU General Public License v3 (GPLv3)
Classifier: Operating System :: OS Independent
Classifier: Topic :: Scientific/Engineering :: Electronic Design Automation (EDA)
